<?xml version="1.0" encoding="utf-8"?>
<!--© DNB-->
<!--Taxonomy Creation Date UTC 2023-06-28T09:26:36+02:00-->
<link:linkbase xmlns:xsi="http://www.w3.org/2001/XMLSchema-instance" xmlns:xlink="http://www.w3.org/1999/xlink" xmlns:link="http://www.xbrl.org/2003/linkbase" xsi:schemaLocation="http://www.xbrl.org/2003/linkbase http://www.xbrl.org/2003/xbrl-linkbase-2003-12-31.xsd">
  <link:labelLink xlink:type="extended" xlink:role="http://www.xbrl.org/2003/role/link">
    <link:loc xlink:type="locator" xlink:href="mem.xsd#dnb_mem017" xlink:label="loc_dnb_mem017" />
    <link:label xlink:type="resource" xlink:label="label_dnb_mem017" xml:lang="en" xlink:role="http://www.xbrl.org/2003/role/label">Not applicable / All or Total</link:label>
    <link:labelArc xlink:type="arc" xlink:arcrole="http://www.xbrl.org/2003/arcrole/concept-label" xlink:from="loc_dnb_mem017" xlink:to="label_dnb_mem017" />
    <link:label xlink:type="resource" xlink:label="label_dnb_mem017_2" xml:lang="en" xlink:role="http://www.xbrl.org/2003/role/documentation">NAP-ALL-TOT</link:label>
    <link:labelArc xlink:type="arc" xlink:arcrole="http://www.xbrl.org/2003/arcrole/concept-label" xlink:from="loc_dnb_mem017" xlink:to="label_dnb_mem017_2" />
    <link:loc xlink:type="locator" xlink:href="mem.xsd#dnb_mem018" xlink:label="loc_dnb_mem018" />
    <link:label xlink:type="resource" xlink:label="label_dnb_mem018" xml:lang="en" xlink:role="http://www.xbrl.org/2003/role/label">Pw artikel 126 - Wvb artikel 121</link:label>
    <link:labelArc xlink:type="arc" xlink:arcrole="http://www.xbrl.org/2003/arcrole/concept-label" xlink:from="loc_dnb_mem018" xlink:to="label_dnb_mem018" />
    <link:label xlink:type="resource" xlink:label="label_dnb_mem018_2" xml:lang="en" xlink:role="http://www.xbrl.org/2003/role/documentation">MEM018</link:label>
    <link:labelArc xlink:type="arc" xlink:arcrole="http://www.xbrl.org/2003/arcrole/concept-label" xlink:from="loc_dnb_mem018" xlink:to="label_dnb_mem018_2" />
    <link:loc xlink:type="locator" xlink:href="mem.xsd#dnb_mem019" xlink:label="loc_dnb_mem019" />
    <link:label xlink:type="resource" xlink:label="label_dnb_mem019" xml:lang="en" xlink:role="http://www.xbrl.org/2003/role/label">Pw artikel 127 - Wvb artikel 122</link:label>
    <link:labelArc xlink:type="arc" xlink:arcrole="http://www.xbrl.org/2003/arcrole/concept-label" xlink:from="loc_dnb_mem019" xlink:to="label_dnb_mem019" />
    <link:label xlink:type="resource" xlink:label="label_dnb_mem019_2" xml:lang="en" xlink:role="http://www.xbrl.org/2003/role/documentation">MEM019</link:label>
    <link:labelArc xlink:type="arc" xlink:arcrole="http://www.xbrl.org/2003/arcrole/concept-label" xlink:from="loc_dnb_mem019" xlink:to="label_dnb_mem019_2" />
    <link:loc xlink:type="locator" xlink:href="mem.xsd#dnb_mem020" xlink:label="loc_dnb_mem020" />
    <link:label xlink:type="resource" xlink:label="label_dnb_mem020" xml:lang="en" xlink:role="http://www.xbrl.org/2003/role/label">Pw artikel 128 - Wvb artikel 123</link:label>
    <link:labelArc xlink:type="arc" xlink:arcrole="http://www.xbrl.org/2003/arcrole/concept-label" xlink:from="loc_dnb_mem020" xlink:to="label_dnb_mem020" />
    <link:label xlink:type="resource" xlink:label="label_dnb_mem020_2" xml:lang="en" xlink:role="http://www.xbrl.org/2003/role/documentation">MEM020</link:label>
    <link:labelArc xlink:type="arc" xlink:arcrole="http://www.xbrl.org/2003/arcrole/concept-label" xlink:from="loc_dnb_mem020" xlink:to="label_dnb_mem020_2" />
    <link:loc xlink:type="locator" xlink:href="mem.xsd#dnb_mem021" xlink:label="loc_dnb_mem021" />
    <link:label xlink:type="resource" xlink:label="label_dnb_mem021" xml:lang="en" xlink:role="http://www.xbrl.org/2003/role/label">Pw artikel 129 - Wvb artikel 124</link:label>
    <link:labelArc xlink:type="arc" xlink:arcrole="http://www.xbrl.org/2003/arcrole/concept-label" xlink:from="loc_dnb_mem021" xlink:to="label_dnb_mem021" />
    <link:label xlink:type="resource" xlink:label="label_dnb_mem021_2" xml:lang="en" xlink:role="http://www.xbrl.org/2003/role/documentation">MEM021</link:label>
    <link:labelArc xlink:type="arc" xlink:arcrole="http://www.xbrl.org/2003/arcrole/concept-label" xlink:from="loc_dnb_mem021" xlink:to="label_dnb_mem021_2" />
    <link:loc xlink:type="locator" xlink:href="mem.xsd#dnb_mem022" xlink:label="loc_dnb_mem022" />
    <link:label xlink:type="resource" xlink:label="label_dnb_mem022" xml:lang="en" xlink:role="http://www.xbrl.org/2003/role/label">Pw artikel 130 - Wvb artikel 125</link:label>
    <link:labelArc xlink:type="arc" xlink:arcrole="http://www.xbrl.org/2003/arcrole/concept-label" xlink:from="loc_dnb_mem022" xlink:to="label_dnb_mem022" />
    <link:label xlink:type="resource" xlink:label="label_dnb_mem022_2" xml:lang="en" xlink:role="http://www.xbrl.org/2003/role/documentation">MEM022</link:label>
    <link:labelArc xlink:type="arc" xlink:arcrole="http://www.xbrl.org/2003/arcrole/concept-label" xlink:from="loc_dnb_mem022" xlink:to="label_dnb_mem022_2" />
    <link:loc xlink:type="locator" xlink:href="mem.xsd#dnb_mem023" xlink:label="loc_dnb_mem023" />
    <link:label xlink:type="resource" xlink:label="label_dnb_mem023" xml:lang="en" xlink:role="http://www.xbrl.org/2003/role/label">Pw artikel 131 - Wvb artikel 126</link:label>
    <link:labelArc xlink:type="arc" xlink:arcrole="http://www.xbrl.org/2003/arcrole/concept-label" xlink:from="loc_dnb_mem023" xlink:to="label_dnb_mem023" />
    <link:label xlink:type="resource" xlink:label="label_dnb_mem023_2" xml:lang="en" xlink:role="http://www.xbrl.org/2003/role/documentation">MEM023</link:label>
    <link:labelArc xlink:type="arc" xlink:arcrole="http://www.xbrl.org/2003/arcrole/concept-label" xlink:from="loc_dnb_mem023" xlink:to="label_dnb_mem023_2" />
    <link:loc xlink:type="locator" xlink:href="mem.xsd#dnb_mem024" xlink:label="loc_dnb_mem024" />
    <link:label xlink:type="resource" xlink:label="label_dnb_mem024" xml:lang="en" xlink:role="http://www.xbrl.org/2003/role/label">Pw artikel 132 - Wvb artikel 127</link:label>
    <link:labelArc xlink:type="arc" xlink:arcrole="http://www.xbrl.org/2003/arcrole/concept-label" xlink:from="loc_dnb_mem024" xlink:to="label_dnb_mem024" />
    <link:label xlink:type="resource" xlink:label="label_dnb_mem024_2" xml:lang="en" xlink:role="http://www.xbrl.org/2003/role/documentation">MEM024</link:label>
    <link:labelArc xlink:type="arc" xlink:arcrole="http://www.xbrl.org/2003/arcrole/concept-label" xlink:from="loc_dnb_mem024" xlink:to="label_dnb_mem024_2" />
    <link:loc xlink:type="locator" xlink:href="mem.xsd#dnb_mem025" xlink:label="loc_dnb_mem025" />
    <link:label xlink:type="resource" xlink:label="label_dnb_mem025" xml:lang="en" xlink:role="http://www.xbrl.org/2003/role/label">Pw artikel 133 - Wvb artikel 128</link:label>
    <link:labelArc xlink:type="arc" xlink:arcrole="http://www.xbrl.org/2003/arcrole/concept-label" xlink:from="loc_dnb_mem025" xlink:to="label_dnb_mem025" />
    <link:label xlink:type="resource" xlink:label="label_dnb_mem025_2" xml:lang="en" xlink:role="http://www.xbrl.org/2003/role/documentation">MEM025</link:label>
    <link:labelArc xlink:type="arc" xlink:arcrole="http://www.xbrl.org/2003/arcrole/concept-label" xlink:from="loc_dnb_mem025" xlink:to="label_dnb_mem025_2" />
    <link:loc xlink:type="locator" xlink:href="mem.xsd#dnb_mem026" xlink:label="loc_dnb_mem026" />
    <link:label xlink:type="resource" xlink:label="label_dnb_mem026" xml:lang="en" xlink:role="http://www.xbrl.org/2003/role/label">Pw artikel 134 - Wvb artikel 129</link:label>
    <link:labelArc xlink:type="arc" xlink:arcrole="http://www.xbrl.org/2003/arcrole/concept-label" xlink:from="loc_dnb_mem026" xlink:to="label_dnb_mem026" />
    <link:label xlink:type="resource" xlink:label="label_dnb_mem026_2" xml:lang="en" xlink:role="http://www.xbrl.org/2003/role/documentation">MEM026</link:label>
    <link:labelArc xlink:type="arc" xlink:arcrole="http://www.xbrl.org/2003/arcrole/concept-label" xlink:from="loc_dnb_mem026" xlink:to="label_dnb_mem026_2" />
    <link:loc xlink:type="locator" xlink:href="mem.xsd#dnb_mem027" xlink:label="loc_dnb_mem027" />
    <link:label xlink:type="resource" xlink:label="label_dnb_mem027" xml:lang="en" xlink:role="http://www.xbrl.org/2003/role/label">Pw artikel 135 - Wvb artikel 130</link:label>
    <link:labelArc xlink:type="arc" xlink:arcrole="http://www.xbrl.org/2003/arcrole/concept-label" xlink:from="loc_dnb_mem027" xlink:to="label_dnb_mem027" />
    <link:label xlink:type="resource" xlink:label="label_dnb_mem027_2" xml:lang="en" xlink:role="http://www.xbrl.org/2003/role/documentation">MEM027</link:label>
    <link:labelArc xlink:type="arc" xlink:arcrole="http://www.xbrl.org/2003/arcrole/concept-label" xlink:from="loc_dnb_mem027" xlink:to="label_dnb_mem027_2" />
    <link:loc xlink:type="locator" xlink:href="mem.xsd#dnb_mem028" xlink:label="loc_dnb_mem028" />
    <link:label xlink:type="resource" xlink:label="label_dnb_mem028" xml:lang="en" xlink:role="http://www.xbrl.org/2003/role/label">Pw artikel 136 - Wvb artikel 131</link:label>
    <link:labelArc xlink:type="arc" xlink:arcrole="http://www.xbrl.org/2003/arcrole/concept-label" xlink:from="loc_dnb_mem028" xlink:to="label_dnb_mem028" />
    <link:label xlink:type="resource" xlink:label="label_dnb_mem028_2" xml:lang="en" xlink:role="http://www.xbrl.org/2003/role/documentation">MEM028</link:label>
    <link:labelArc xlink:type="arc" xlink:arcrole="http://www.xbrl.org/2003/arcrole/concept-label" xlink:from="loc_dnb_mem028" xlink:to="label_dnb_mem028_2" />
    <link:loc xlink:type="locator" xlink:href="mem.xsd#dnb_mem029" xlink:label="loc_dnb_mem029" />
    <link:label xlink:type="resource" xlink:label="label_dnb_mem029" xml:lang="en" xlink:role="http://www.xbrl.org/2003/role/label">Pw artikel 137 - Wvb artikel 132</link:label>
    <link:labelArc xlink:type="arc" xlink:arcrole="http://www.xbrl.org/2003/arcrole/concept-label" xlink:from="loc_dnb_mem029" xlink:to="label_dnb_mem029" />
    <link:label xlink:type="resource" xlink:label="label_dnb_mem029_2" xml:lang="en" xlink:role="http://www.xbrl.org/2003/role/documentation">MEM029</link:label>
    <link:labelArc xlink:type="arc" xlink:arcrole="http://www.xbrl.org/2003/arcrole/concept-label" xlink:from="loc_dnb_mem029" xlink:to="label_dnb_mem029_2" />
    <link:loc xlink:type="locator" xlink:href="mem.xsd#dnb_mem030" xlink:label="loc_dnb_mem030" />
    <link:label xlink:type="resource" xlink:label="label_dnb_mem030" xml:lang="en" xlink:role="http://www.xbrl.org/2003/role/label">Pw artikel 138 - Wvb artikel 133</link:label>
    <link:labelArc xlink:type="arc" xlink:arcrole="http://www.xbrl.org/2003/arcrole/concept-label" xlink:from="loc_dnb_mem030" xlink:to="label_dnb_mem030" />
    <link:label xlink:type="resource" xlink:label="label_dnb_mem030_2" xml:lang="en" xlink:role="http://www.xbrl.org/2003/role/documentation">MEM030</link:label>
    <link:labelArc xlink:type="arc" xlink:arcrole="http://www.xbrl.org/2003/arcrole/concept-label" xlink:from="loc_dnb_mem030" xlink:to="label_dnb_mem030_2" />
    <link:loc xlink:type="locator" xlink:href="mem.xsd#dnb_mem031" xlink:label="loc_dnb_mem031" />
    <link:label xlink:type="resource" xlink:label="label_dnb_mem031" xml:lang="en" xlink:role="http://www.xbrl.org/2003/role/label">Pw artikel 139 - Wvb artikel 134</link:label>
    <link:labelArc xlink:type="arc" xlink:arcrole="http://www.xbrl.org/2003/arcrole/concept-label" xlink:from="loc_dnb_mem031" xlink:to="label_dnb_mem031" />
    <link:label xlink:type="resource" xlink:label="label_dnb_mem031_2" xml:lang="en" xlink:role="http://www.xbrl.org/2003/role/documentation">MEM031</link:label>
    <link:labelArc xlink:type="arc" xlink:arcrole="http://www.xbrl.org/2003/arcrole/concept-label" xlink:from="loc_dnb_mem031" xlink:to="label_dnb_mem031_2" />
    <link:loc xlink:type="locator" xlink:href="mem.xsd#dnb_mem032" xlink:label="loc_dnb_mem032" />
    <link:label xlink:type="resource" xlink:label="label_dnb_mem032" xml:lang="en" xlink:role="http://www.xbrl.org/2003/role/label">Pw artikel 140 - Wvb artikel 135</link:label>
    <link:labelArc xlink:type="arc" xlink:arcrole="http://www.xbrl.org/2003/arcrole/concept-label" xlink:from="loc_dnb_mem032" xlink:to="label_dnb_mem032" />
    <link:label xlink:type="resource" xlink:label="label_dnb_mem032_2" xml:lang="en" xlink:role="http://www.xbrl.org/2003/role/documentation">MEM032</link:label>
    <link:labelArc xlink:type="arc" xlink:arcrole="http://www.xbrl.org/2003/arcrole/concept-label" xlink:from="loc_dnb_mem032" xlink:to="label_dnb_mem032_2" />
  </link:labelLink>
</link:linkbase>