{
    "documentInfo": {
        "documentType": "https://xbrl.org/2021/xbrl-csv",
        "namespaces": {
            "eba": "http://www.eba.europa.eu",
            "eba_AP": "http://www.eba.europa.eu/xbrl/crr/dict/dom/AP",
            "eba_BA": "http://www.eba.europa.eu/xbrl/crr/dict/dom/BA",
            "eba_BT": "http://www.eba.europa.eu/xbrl/crr/dict/dom/BT",
            "eba_MC": "http://www.eba.europa.eu/xbrl/crr/dict/dom/MC",
            "eba_RP": "http://www.eba.europa.eu/xbrl/crr/dict/dom/RP",
            "eba_TA": "http://www.eba.europa.eu/xbrl/crr/dict/dom/TA",
            "eba_TR": "http://www.eba.europa.eu/xbrl/crr/dict/dom/TR",
            "eba_dim": "http://www.eba.europa.eu/xbrl/crr/dict/dim",
            "eba_met": "http://www.eba.europa.eu/xbrl/crr/dict/met"
        }
    },
    "tableTemplates": {
        "I_05-00": {
            "columns": {
                "datapoint": {
                    "propertyGroups": {
                        "dp441420": {
                            "decimals": "$decimalsMonetary",
                            "dimensions": {
                                "concept": "eba_met:mi459",
                                "eba_dim:BAS": "eba_BA:x9",
                                "eba_dim:MCY": "eba_MC:x971",
                                "eba_dim:TRI": "eba_TR:x37",
                                "unit": "$baseCurrency"
                            },
                            "eba:documentation": {
                                "CellCode": "{I_05.00, r0040, c0010}",
                                "CellID": 135245,
                                "ColumnVID": 79563,
                                "FactVariableID": "441420",
                                "FactVariableVersionID": "460096",
                                "RowVID": 79567,
                                "SheetVID": null,
                                "type": "m"
                            }
                        },
                        "dp441421": {
                            "decimals": "$decimalsMonetary",
                            "dimensions": {
                                "concept": "eba_met:mi459",
                                "eba_dim:BAS": "eba_BA:x9",
                                "eba_dim:MCY": "eba_MC:x972",
                                "eba_dim:TRI": "eba_TR:x40",
                                "unit": "$baseCurrency"
                            },
                            "eba:documentation": {
                                "CellCode": "{I_05.00, r0080, c0010}",
                                "CellID": 135249,
                                "ColumnVID": 79563,
                                "FactVariableID": "441421",
                                "FactVariableVersionID": "460097",
                                "RowVID": 79571,
                                "SheetVID": null,
                                "type": "m"
                            }
                        },
                        "dp459766": {
                            "decimals": "$decimalsMonetary",
                            "dimensions": {
                                "concept": "eba_met:mi53",
                                "eba_dim:BAS": "eba_BA:x29",
                                "eba_dim:MCY": "eba_MC:x1186",
                                "eba_dim:RPR": "eba_RP:x89",
                                "unit": "$baseCurrency"
                            },
                            "eba:documentation": {
                                "CellCode": "{I_05.00, r0100, c0010}",
                                "CellID": 135251,
                                "ColumnVID": 79563,
                                "FactVariableID": "459766",
                                "FactVariableVersionID": "459766",
                                "RowVID": 79573,
                                "SheetVID": null,
                                "type": "m"
                            }
                        },
                        "dp459767": {
                            "decimals": "$decimalsMonetary",
                            "dimensions": {
                                "concept": "eba_met:mi76",
                                "eba_dim:BAS": "eba_BA:x5",
                                "eba_dim:CAL": "eba_AP:x221",
                                "eba_dim:IIP": "eba_BT:x2",
                                "eba_dim:MCY": "eba_MC:x1208",
                                "eba_dim:RPR": "eba_RP:x89",
                                "unit": "$baseCurrency"
                            },
                            "eba:documentation": {
                                "CellCode": "{I_05.00, r0110, c0010}",
                                "CellID": 135252,
                                "ColumnVID": 79563,
                                "FactVariableID": "459767",
                                "FactVariableVersionID": "459767",
                                "RowVID": 79574,
                                "SheetVID": null,
                                "type": "m"
                            }
                        },
                        "dp459768": {
                            "decimals": "$decimalsMonetary",
                            "dimensions": {
                                "concept": "eba_met:mi76",
                                "eba_dim:BAS": "eba_BA:x5",
                                "eba_dim:CAL": "eba_AP:x221",
                                "eba_dim:IIP": "eba_BT:x2",
                                "eba_dim:MCY": "eba_MC:x1208",
                                "eba_dim:RPR": "eba_RP:x89",
                                "eba_dim:TIA": "eba_TA:x104",
                                "unit": "$baseCurrency"
                            },
                            "eba:documentation": {
                                "CellCode": "{I_05.00, r0260, c0010}",
                                "CellID": 135267,
                                "ColumnVID": 79563,
                                "FactVariableID": "459768",
                                "FactVariableVersionID": "459768",
                                "RowVID": 79589,
                                "SheetVID": null,
                                "type": "m"
                            }
                        },
                        "dp459769": {
                            "decimals": "$decimalsMonetary",
                            "dimensions": {
                                "concept": "eba_met:mi76",
                                "eba_dim:BAS": "eba_BA:x5",
                                "eba_dim:CAL": "eba_AP:x221",
                                "eba_dim:IIP": "eba_BT:x2",
                                "eba_dim:MCY": "eba_MC:x1208",
                                "eba_dim:RPR": "eba_RP:x89",
                                "eba_dim:TIA": "eba_TA:x133",
                                "unit": "$baseCurrency"
                            },
                            "eba:documentation": {
                                "CellCode": "{I_05.00, r0140, c0010}",
                                "CellID": 135255,
                                "ColumnVID": 79563,
                                "FactVariableID": "459769",
                                "FactVariableVersionID": "459769",
                                "RowVID": 79577,
                                "SheetVID": null,
                                "type": "m"
                            }
                        },
                        "dp459770": {
                            "decimals": "$decimalsMonetary",
                            "dimensions": {
                                "concept": "eba_met:mi76",
                                "eba_dim:BAS": "eba_BA:x5",
                                "eba_dim:CAL": "eba_AP:x221",
                                "eba_dim:IIP": "eba_BT:x2",
                                "eba_dim:MCY": "eba_MC:x1208",
                                "eba_dim:RPR": "eba_RP:x89",
                                "eba_dim:TIA": "eba_TA:x134",
                                "unit": "$baseCurrency"
                            },
                            "eba:documentation": {
                                "CellCode": "{I_05.00, r0150, c0010}",
                                "CellID": 135256,
                                "ColumnVID": 79563,
                                "FactVariableID": "459770",
                                "FactVariableVersionID": "459770",
                                "RowVID": 79578,
                                "SheetVID": null,
                                "type": "m"
                            }
                        },
                        "dp459771": {
                            "decimals": "$decimalsMonetary",
                            "dimensions": {
                                "concept": "eba_met:mi76",
                                "eba_dim:BAS": "eba_BA:x5",
                                "eba_dim:CAL": "eba_AP:x221",
                                "eba_dim:IIP": "eba_BT:x2",
                                "eba_dim:MCY": "eba_MC:x1208",
                                "eba_dim:RPR": "eba_RP:x89",
                                "eba_dim:TIA": "eba_TA:x135",
                                "unit": "$baseCurrency"
                            },
                            "eba:documentation": {
                                "CellCode": "{I_05.00, r0160, c0010}",
                                "CellID": 135257,
                                "ColumnVID": 79563,
                                "FactVariableID": "459771",
                                "FactVariableVersionID": "459771",
                                "RowVID": 79579,
                                "SheetVID": null,
                                "type": "m"
                            }
                        },
                        "dp459772": {
                            "decimals": "$decimalsMonetary",
                            "dimensions": {
                                "concept": "eba_met:mi76",
                                "eba_dim:BAS": "eba_BA:x5",
                                "eba_dim:CAL": "eba_AP:x221",
                                "eba_dim:IIP": "eba_BT:x2",
                                "eba_dim:MCY": "eba_MC:x1208",
                                "eba_dim:RPR": "eba_RP:x89",
                                "eba_dim:TIA": "eba_TA:x136",
                                "unit": "$baseCurrency"
                            },
                            "eba:documentation": {
                                "CellCode": "{I_05.00, r0170, c0010}",
                                "CellID": 135258,
                                "ColumnVID": 79563,
                                "FactVariableID": "459772",
                                "FactVariableVersionID": "459772",
                                "RowVID": 79580,
                                "SheetVID": null,
                                "type": "m"
                            }
                        },
                        "dp459773": {
                            "decimals": "$decimalsMonetary",
                            "dimensions": {
                                "concept": "eba_met:mi76",
                                "eba_dim:BAS": "eba_BA:x5",
                                "eba_dim:CAL": "eba_AP:x221",
                                "eba_dim:IIP": "eba_BT:x2",
                                "eba_dim:MCY": "eba_MC:x1208",
                                "eba_dim:RPR": "eba_RP:x89",
                                "eba_dim:TIA": "eba_TA:x137",
                                "unit": "$baseCurrency"
                            },
                            "eba:documentation": {
                                "CellCode": "{I_05.00, r0180, c0010}",
                                "CellID": 135259,
                                "ColumnVID": 79563,
                                "FactVariableID": "459773",
                                "FactVariableVersionID": "459773",
                                "RowVID": 79581,
                                "SheetVID": null,
                                "type": "m"
                            }
                        },
                        "dp459774": {
                            "decimals": "$decimalsMonetary",
                            "dimensions": {
                                "concept": "eba_met:mi76",
                                "eba_dim:BAS": "eba_BA:x5",
                                "eba_dim:CAL": "eba_AP:x221",
                                "eba_dim:IIP": "eba_BT:x2",
                                "eba_dim:MCY": "eba_MC:x1208",
                                "eba_dim:RPR": "eba_RP:x89",
                                "eba_dim:TIA": "eba_TA:x138",
                                "unit": "$baseCurrency"
                            },
                            "eba:documentation": {
                                "CellCode": "{I_05.00, r0190, c0010}",
                                "CellID": 135260,
                                "ColumnVID": 79563,
                                "FactVariableID": "459774",
                                "FactVariableVersionID": "459774",
                                "RowVID": 79582,
                                "SheetVID": null,
                                "type": "m"
                            }
                        },
                        "dp459775": {
                            "decimals": "$decimalsMonetary",
                            "dimensions": {
                                "concept": "eba_met:mi76",
                                "eba_dim:BAS": "eba_BA:x5",
                                "eba_dim:CAL": "eba_AP:x221",
                                "eba_dim:IIP": "eba_BT:x2",
                                "eba_dim:MCY": "eba_MC:x1208",
                                "eba_dim:RPR": "eba_RP:x89",
                                "eba_dim:TIA": "eba_TA:x139",
                                "unit": "$baseCurrency"
                            },
                            "eba:documentation": {
                                "CellCode": "{I_05.00, r0200, c0010}",
                                "CellID": 135261,
                                "ColumnVID": 79563,
                                "FactVariableID": "459775",
                                "FactVariableVersionID": "459775",
                                "RowVID": 79583,
                                "SheetVID": null,
                                "type": "m"
                            }
                        },
                        "dp459776": {
                            "decimals": "$decimalsMonetary",
                            "dimensions": {
                                "concept": "eba_met:mi76",
                                "eba_dim:BAS": "eba_BA:x5",
                                "eba_dim:CAL": "eba_AP:x221",
                                "eba_dim:IIP": "eba_BT:x2",
                                "eba_dim:MCY": "eba_MC:x1208",
                                "eba_dim:RPR": "eba_RP:x89",
                                "eba_dim:TIA": "eba_TA:x140",
                                "unit": "$baseCurrency"
                            },
                            "eba:documentation": {
                                "CellCode": "{I_05.00, r0210, c0010}",
                                "CellID": 135262,
                                "ColumnVID": 79563,
                                "FactVariableID": "459776",
                                "FactVariableVersionID": "459776",
                                "RowVID": 79584,
                                "SheetVID": null,
                                "type": "m"
                            }
                        },
                        "dp459777": {
                            "decimals": "$decimalsMonetary",
                            "dimensions": {
                                "concept": "eba_met:mi76",
                                "eba_dim:BAS": "eba_BA:x5",
                                "eba_dim:CAL": "eba_AP:x221",
                                "eba_dim:IIP": "eba_BT:x2",
                                "eba_dim:MCY": "eba_MC:x1208",
                                "eba_dim:RPR": "eba_RP:x89",
                                "eba_dim:TIA": "eba_TA:x141",
                                "unit": "$baseCurrency"
                            },
                            "eba:documentation": {
                                "CellCode": "{I_05.00, r0220, c0010}",
                                "CellID": 135263,
                                "ColumnVID": 79563,
                                "FactVariableID": "459777",
                                "FactVariableVersionID": "459777",
                                "RowVID": 79585,
                                "SheetVID": null,
                                "type": "m"
                            }
                        },
                        "dp459778": {
                            "decimals": "$decimalsMonetary",
                            "dimensions": {
                                "concept": "eba_met:mi76",
                                "eba_dim:BAS": "eba_BA:x5",
                                "eba_dim:CAL": "eba_AP:x221",
                                "eba_dim:IIP": "eba_BT:x2",
                                "eba_dim:MCY": "eba_MC:x1208",
                                "eba_dim:RPR": "eba_RP:x89",
                                "eba_dim:TIA": "eba_TA:x142",
                                "unit": "$baseCurrency"
                            },
                            "eba:documentation": {
                                "CellCode": "{I_05.00, r0230, c0010}",
                                "CellID": 135264,
                                "ColumnVID": 79563,
                                "FactVariableID": "459778",
                                "FactVariableVersionID": "459778",
                                "RowVID": 79586,
                                "SheetVID": null,
                                "type": "m"
                            }
                        },
                        "dp459779": {
                            "decimals": "$decimalsMonetary",
                            "dimensions": {
                                "concept": "eba_met:mi76",
                                "eba_dim:BAS": "eba_BA:x5",
                                "eba_dim:CAL": "eba_AP:x221",
                                "eba_dim:IIP": "eba_BT:x2",
                                "eba_dim:MCY": "eba_MC:x1208",
                                "eba_dim:RPR": "eba_RP:x89",
                                "eba_dim:TIA": "eba_TA:x143",
                                "unit": "$baseCurrency"
                            },
                            "eba:documentation": {
                                "CellCode": "{I_05.00, r0240, c0010}",
                                "CellID": 135265,
                                "ColumnVID": 79563,
                                "FactVariableID": "459779",
                                "FactVariableVersionID": "459779",
                                "RowVID": 79587,
                                "SheetVID": null,
                                "type": "m"
                            }
                        },
                        "dp459780": {
                            "decimals": "$decimalsMonetary",
                            "dimensions": {
                                "concept": "eba_met:mi76",
                                "eba_dim:BAS": "eba_BA:x5",
                                "eba_dim:CAL": "eba_AP:x221",
                                "eba_dim:IIP": "eba_BT:x2",
                                "eba_dim:MCY": "eba_MC:x1208",
                                "eba_dim:RPR": "eba_RP:x89",
                                "eba_dim:TIA": "eba_TA:x144",
                                "unit": "$baseCurrency"
                            },
                            "eba:documentation": {
                                "CellCode": "{I_05.00, r0250, c0010}",
                                "CellID": 135266,
                                "ColumnVID": 79563,
                                "FactVariableID": "459780",
                                "FactVariableVersionID": "459780",
                                "RowVID": 79588,
                                "SheetVID": null,
                                "type": "m"
                            }
                        },
                        "dp459781": {
                            "decimals": "$decimalsMonetary",
                            "dimensions": {
                                "concept": "eba_met:mi76",
                                "eba_dim:BAS": "eba_BA:x5",
                                "eba_dim:CAL": "eba_AP:x221",
                                "eba_dim:IIP": "eba_BT:x2",
                                "eba_dim:MCY": "eba_MC:x1208",
                                "eba_dim:RPR": "eba_RP:x89",
                                "eba_dim:TIA": "eba_TA:x146",
                                "unit": "$baseCurrency"
                            },
                            "eba:documentation": {
                                "CellCode": "{I_05.00, r0270, c0010}",
                                "CellID": 135268,
                                "ColumnVID": 79563,
                                "FactVariableID": "459781",
                                "FactVariableVersionID": "459781",
                                "RowVID": 79590,
                                "SheetVID": null,
                                "type": "m"
                            }
                        },
                        "dp459782": {
                            "decimals": "$decimalsMonetary",
                            "dimensions": {
                                "concept": "eba_met:mi76",
                                "eba_dim:BAS": "eba_BA:x5",
                                "eba_dim:CAL": "eba_AP:x221",
                                "eba_dim:IIP": "eba_BT:x2",
                                "eba_dim:MCY": "eba_MC:x1208",
                                "eba_dim:RPR": "eba_RP:x89",
                                "eba_dim:TIA": "eba_TA:x147",
                                "unit": "$baseCurrency"
                            },
                            "eba:documentation": {
                                "CellCode": "{I_05.00, r0280, c0010}",
                                "CellID": 135269,
                                "ColumnVID": 79563,
                                "FactVariableID": "459782",
                                "FactVariableVersionID": "459782",
                                "RowVID": 79591,
                                "SheetVID": null,
                                "type": "m"
                            }
                        },
                        "dp459783": {
                            "decimals": "$decimalsMonetary",
                            "dimensions": {
                                "concept": "eba_met:mi76",
                                "eba_dim:BAS": "eba_BA:x5",
                                "eba_dim:CAL": "eba_AP:x221",
                                "eba_dim:IIP": "eba_BT:x2",
                                "eba_dim:MCY": "eba_MC:x1208",
                                "eba_dim:RPR": "eba_RP:x89",
                                "eba_dim:TIA": "eba_TA:x148",
                                "unit": "$baseCurrency"
                            },
                            "eba:documentation": {
                                "CellCode": "{I_05.00, r0290, c0010}",
                                "CellID": 135270,
                                "ColumnVID": 79563,
                                "FactVariableID": "459783",
                                "FactVariableVersionID": "459783",
                                "RowVID": 79592,
                                "SheetVID": null,
                                "type": "m"
                            }
                        },
                        "dp459784": {
                            "decimals": "$decimalsMonetary",
                            "dimensions": {
                                "concept": "eba_met:mi76",
                                "eba_dim:BAS": "eba_BA:x5",
                                "eba_dim:CAL": "eba_AP:x221",
                                "eba_dim:IIP": "eba_BT:x5",
                                "eba_dim:MCY": "eba_MC:x1208",
                                "eba_dim:RPR": "eba_RP:x89",
                                "unit": "$baseCurrency"
                            },
                            "eba:documentation": {
                                "CellCode": "{I_05.00, r0120, c0010}",
                                "CellID": 135253,
                                "ColumnVID": 79563,
                                "FactVariableID": "459784",
                                "FactVariableVersionID": "459784",
                                "RowVID": 79575,
                                "SheetVID": null,
                                "type": "m"
                            }
                        },
                        "dp459785": {
                            "decimals": "$decimalsMonetary",
                            "dimensions": {
                                "concept": "eba_met:mi76",
                                "eba_dim:BAS": "eba_BA:x5",
                                "eba_dim:CAL": "eba_AP:x221",
                                "eba_dim:IIP": "eba_BT:x5",
                                "eba_dim:MCY": "eba_MC:x1209",
                                "eba_dim:RPR": "eba_RP:x89",
                                "unit": "$baseCurrency"
                            },
                            "eba:documentation": {
                                "CellCode": "{I_05.00, r0130, c0010}",
                                "CellID": 135254,
                                "ColumnVID": 79563,
                                "FactVariableID": "459785",
                                "FactVariableVersionID": "459785",
                                "RowVID": 79576,
                                "SheetVID": null,
                                "type": "m"
                            }
                        },
                        "dp460042": {
                            "decimals": "$decimalsMonetary",
                            "dimensions": {
                                "concept": "eba_met:mi459",
                                "eba_dim:BAS": "eba_BA:x9",
                                "eba_dim:MCK": "eba_MC:x976",
                                "eba_dim:MCY": "eba_MC:x971",
                                "eba_dim:RPR": "eba_RP:x89",
                                "eba_dim:TRI": "eba_TR:x38",
                                "unit": "$baseCurrency"
                            },
                            "eba:documentation": {
                                "CellCode": "{I_05.00, r0020, c0010}",
                                "CellID": 135243,
                                "ColumnVID": 79563,
                                "FactVariableID": "460042",
                                "FactVariableVersionID": "460042",
                                "RowVID": 79565,
                                "SheetVID": null,
                                "type": "m"
                            }
                        },
                        "dp460057": {
                            "decimals": "$decimalsMonetary",
                            "dimensions": {
                                "concept": "eba_met:mi459",
                                "eba_dim:BAS": "eba_BA:x9",
                                "eba_dim:MCK": "eba_MC:x977",
                                "eba_dim:MCY": "eba_MC:x971",
                                "eba_dim:RPR": "eba_RP:x89",
                                "eba_dim:TRI": "eba_TR:x38",
                                "unit": "$baseCurrency"
                            },
                            "eba:documentation": {
                                "CellCode": "{I_05.00, r0030, c0010}",
                                "CellID": 135244,
                                "ColumnVID": 79563,
                                "FactVariableID": "460057",
                                "FactVariableVersionID": "460057",
                                "RowVID": 79566,
                                "SheetVID": null,
                                "type": "m"
                            }
                        },
                        "dp460063": {
                            "decimals": "$decimalsMonetary",
                            "dimensions": {
                                "concept": "eba_met:mi459",
                                "eba_dim:BAS": "eba_BA:x9",
                                "eba_dim:MCK": "eba_MC:x1213",
                                "eba_dim:MCY": "eba_MC:x973",
                                "eba_dim:TRI": "eba_TR:x42",
                                "unit": "$baseCurrency"
                            },
                            "eba:documentation": {
                                "CellCode": "{I_05.00, r0060, c0010}",
                                "CellID": 135247,
                                "ColumnVID": 79563,
                                "FactVariableID": "460063",
                                "FactVariableVersionID": "460063",
                                "RowVID": 79569,
                                "SheetVID": null,
                                "type": "m"
                            }
                        },
                        "dp460091": {
                            "decimals": "$decimalsMonetary",
                            "dimensions": {
                                "concept": "eba_met:mi459",
                                "eba_dim:BAS": "eba_BA:x9",
                                "eba_dim:MCY": "eba_MC:x971",
                                "eba_dim:RPR": "eba_RP:x89",
                                "eba_dim:TRI": "eba_TR:x44",
                                "unit": "$baseCurrency"
                            },
                            "eba:documentation": {
                                "CellCode": "{I_05.00, r0010, c0010}",
                                "CellID": 135242,
                                "ColumnVID": 79563,
                                "FactVariableID": "460091",
                                "FactVariableVersionID": "460091",
                                "RowVID": 79564,
                                "SheetVID": null,
                                "type": "m"
                            }
                        },
                        "dp460095": {
                            "decimals": "$decimalsMonetary",
                            "dimensions": {
                                "concept": "eba_met:mi459",
                                "eba_dim:BAS": "eba_BA:x9",
                                "eba_dim:MCY": "eba_MC:x971",
                                "eba_dim:TRI": "eba_TR:x36",
                                "unit": "$baseCurrency"
                            },
                            "eba:documentation": {
                                "CellCode": "{I_05.00, r0050, c0010}",
                                "CellID": 135246,
                                "ColumnVID": 79563,
                                "FactVariableID": "460095",
                                "FactVariableVersionID": "460095",
                                "RowVID": 79568,
                                "SheetVID": null,
                                "type": "m"
                            }
                        },
                        "dp460098": {
                            "decimals": "$decimalsMonetary",
                            "dimensions": {
                                "concept": "eba_met:mi459",
                                "eba_dim:BAS": "eba_BA:x9",
                                "eba_dim:MCY": "eba_MC:x972",
                                "eba_dim:TRI": "eba_TR:x65",
                                "unit": "$baseCurrency"
                            },
                            "eba:documentation": {
                                "CellCode": "{I_05.00, r0070, c0010}",
                                "CellID": 135248,
                                "ColumnVID": 79563,
                                "FactVariableID": "460098",
                                "FactVariableVersionID": "460098",
                                "RowVID": 79570,
                                "SheetVID": null,
                                "type": "m"
                            }
                        },
                        "dp460099": {
                            "decimals": "$decimalsMonetary",
                            "dimensions": {
                                "concept": "eba_met:mi459",
                                "eba_dim:BAS": "eba_BA:x9",
                                "eba_dim:MCY": "eba_MC:x973",
                                "eba_dim:TRI": "eba_TR:x41",
                                "unit": "$baseCurrency"
                            },
                            "eba:documentation": {
                                "CellCode": "{I_05.00, r0090, c0010}",
                                "CellID": 135250,
                                "ColumnVID": 79563,
                                "FactVariableID": "460099",
                                "FactVariableVersionID": "460099",
                                "RowVID": 79572,
                                "SheetVID": null,
                                "type": "m"
                            }
                        }
                    }
                },
                "factValue": {
                    "dimensions": {},
                    "propertiesFrom": [
                        "datapoint"
                    ]
                }
            }
        }
    }
}